repols/__init__.py
repols/cli.py
repols/csv.py
repols/insort.py
repols/list_repositories.py
test/__init__.py
test/list_item.py
test/test_csv.py
test/test_include_metadata.py
test/test_insort.py
test/test_repository_metadata.py
test/test_sort_repos.py
repols-1.1.2.dist-info/LICENSE.txt
repols-1.1.2.dist-info/METADATA
repols-1.1.2.dist-info/WHEEL
repols-1.1.2.dist-info/entry_points.txt
repols-1.1.2.dist-info/top_level.txt
repols-1.1.2.dist-info/RECORD
