Metadata-Version: 2.1
Name: repols
Version: 1.1.2
Summary: List GitHub repositories filtered by team
Home-page: https://github.com/deriksson/repols
Author: Daniel Eriksson
Author-email: gustaf.daniel.eriksson@gmail.com
License: UNKNOWN
Platform: UNKNOWN
Classifier: Programming Language :: Python :: 3
Classifier: License :: OSI Approved :: MIT License
Classifier: Operating System :: OS Independent
Requires-Python: >=3.6
Requires-Dist: Click (>=7.0)
Requires-Dist: PyGithub
